graphrag_ui/README-CN.md
graphrag_ui/README.md
graphrag_ui/api.py
graphrag_ui/app.py
graphrag_ui/index_app.py
graphrag_ui/requirements.txt
graphrag_ui/settings-example.yaml
graphrag_ui/web.py
graphrag_ui/indexing/.env
graphrag_ui/indexing/settings.yaml
graphrag_ui/indexing/input/test.txt
graphrag_ui/indexing/output/empty.md
graphrag_ui/indexing/prompts/claim_extraction.txt
graphrag_ui/indexing/prompts/community_report.txt
graphrag_ui/indexing/prompts/entity_extraction.txt
graphrag_ui/indexing/prompts/summarize_descriptions.txt
graphrag_ui/lancedb/empty.md
graphrag_ui-0.1.3.dist-info/LICENSE
graphrag_ui-0.1.3.dist-info/METADATA
graphrag_ui-0.1.3.dist-info/WHEEL
graphrag_ui-0.1.3.dist-info/entry_points.txt
graphrag_ui-0.1.3.dist-info/top_level.txt
graphrag_ui-0.1.3.dist-info/RECORD
