Metadata-Version: 2.1
Name: graphrag-ui
Version: 0.1.3
Summary: The latest graphrag interface is used, using the local ollama to provide the LLM interface
Home-page: https://github.com/wade1010/graphrag-ui
Author: wade1010
Author-email: 640297@qq.com
License: MIT
Keywords: graphrag ollma ui local ai
Classifier: Programming Language :: Python :: 3
Classifier: License :: OSI Approved :: MIT License
Classifier: Operating System :: OS Independent
Requires-Python: >=3.8
License-File: LICENSE
Requires-Dist: gradio==4.43.0
Requires-Dist: fastapi==0.112.4
Requires-Dist: uvicorn==0.30.6
Requires-Dist: python-dotenv==1.0.1
Requires-Dist: pydantic==2.9.0
Requires-Dist: pandas==2.2.2
Requires-Dist: tiktoken==0.7.0
Requires-Dist: langchain-community==0.2.16
Requires-Dist: aiohttp==3.10.5
Requires-Dist: PyYAML==6.0.2
Requires-Dist: requests==2.32.3
Requires-Dist: duckduckgo-search==6.2.11
Requires-Dist: ollama==0.3.2
Requires-Dist: plotly==5.24.0
